MANIFEST.in
README.rst
setup.py
docs/HISTORY.txt
docs/LICENSE.GPL
docs/LICENSE.txt
src/affinitic/__init__.py
src/affinitic.simplecookiecuttr.egg-info/PKG-INFO
src/affinitic.simplecookiecuttr.egg-info/SOURCES.txt
src/affinitic.simplecookiecuttr.egg-info/dependency_links.txt
src/affinitic.simplecookiecuttr.egg-info/namespace_packages.txt
src/affinitic.simplecookiecuttr.egg-info/not-zip-safe
src/affinitic.simplecookiecuttr.egg-info/requires.txt
src/affinitic.simplecookiecuttr.egg-info/top_level.txt
src/affinitic/simplecookiecuttr/__init__.py
src/affinitic/simplecookiecuttr/configure.zcml
src/affinitic/simplecookiecuttr/interfaces.py
src/affinitic/simplecookiecuttr/profiles.zcml
src/affinitic/simplecookiecuttr/browser/__init__.py
src/affinitic/simplecookiecuttr/browser/configure.zcml
src/affinitic/simplecookiecuttr/browser/viewlet.py
src/affinitic/simplecookiecuttr/profiles/default/browserlayer.xml
src/affinitic/simplecookiecuttr/profiles/default/cssregistry.xml
src/affinitic/simplecookiecuttr/profiles/default/jsregistry.xml
src/affinitic/simplecookiecuttr/profiles/default/metadata.xml
src/affinitic/simplecookiecuttr/profiles/default/propertiestool.xml
src/affinitic/simplecookiecuttr/static/cookiecuttr.css
src/affinitic/simplecookiecuttr/static/jquery.cookie.js
src/affinitic/simplecookiecuttr/static/jquery.cookiecuttr.js