Metadata-Version: 1.1
Name: affinitic.simplecookiecuttr
Version: 0.1
Summary: Basic integration of jquery.cookiecuttr.js for Plone 3
Home-page: https://github.com/affinitic/affinitic.simplecookiecuttr
Author: Affinitic
Author-email: info@affinitic.be
License: gpl
Keywords: Affinitic
Platform: UNKNOWN
Classifier: Framework :: Plone
Classifier: Programming Language :: Python
Classifier: Topic :: Software Development :: Libraries :: Python Modules
